{
  "timestamp": "2026-05-06T04:54:31.220063",
  "benchmark": "rcaeval-re2-tt",
  "dataset": "tt",
  "total_elapsed_seconds": 502.65,
  "summary": {
    "ours": {
      "total": 5,
      "ac1": 5,
      "ac3": 5,
      "elapsed": [
        111.8,
        104.73,
        88.47,
        108.43,
        73.38
      ],
      "by_fault": {
        "mem": {
          "total": 5,
          "ac1": 5,
          "ac3": 5,
          "ac1_rate": 1.0,
          "ac3_rate": 1.0
        }
      },
      "ac1_rate": 1.0,
      "ac3_rate": 1.0,
      "avg_elapsed": 97.36
    }
  },
  "results": [
    {
      "system": "ours",
      "benchmark": "rcaeval-re2-tt",
      "case": "ts-auth-service_mem_1",
      "gt_service": "ts-auth-service",
      "gt_fault": "mem",
      "elapsed_seconds": 111.8,
      "evaluation": {
        "ac_at_1": true,
        "ac_at_3": true,
        "path_accuracy": null,
        "fp_handled": null,
        "top_confidence": 0.45,
        "verdict": "weak-evidence",
        "ground_truth_root_cause": "ts-auth-service",
        "predicted_top_cause_service": "ts-auth-service",
        "predicted_top_cause_excerpt": "ts-auth-service",
        "predicted_path": [
          "ts-auth-service",
          "ts-preserve-service"
        ],
        "predicted_path_length": 2,
        "elapsed_seconds": 111.8,
        "gt_fault": "mem"
      }
    },
    {
      "system": "ours",
      "benchmark": "rcaeval-re2-tt",
      "case": "ts-order-service_mem_1",
      "gt_service": "ts-order-service",
      "gt_fault": "mem",
      "elapsed_seconds": 104.73,
      "evaluation": {
        "ac_at_1": true,
        "ac_at_3": true,
        "path_accuracy": null,
        "fp_handled": null,
        "top_confidence": 0.6,
        "verdict": "revised",
        "ground_truth_root_cause": "ts-order-service",
        "predicted_top_cause_service": "ts-order-service",
        "predicted_top_cause_excerpt": "ts-order-service",
        "predicted_path": [
          "ts-order-service",
          "ts-preserve-service"
        ],
        "predicted_path_length": 2,
        "elapsed_seconds": 104.73,
        "gt_fault": "mem"
      }
    },
    {
      "system": "ours",
      "benchmark": "rcaeval-re2-tt",
      "case": "ts-route-service_mem_1",
      "gt_service": "ts-route-service",
      "gt_fault": "mem",
      "elapsed_seconds": 88.47,
      "evaluation": {
        "ac_at_1": true,
        "ac_at_3": true,
        "path_accuracy": null,
        "fp_handled": null,
        "top_confidence": 0.6,
        "verdict": "revised",
        "ground_truth_root_cause": "ts-route-service",
        "predicted_top_cause_service": "ts-route-service",
        "predicted_top_cause_excerpt": "ts-route-service",
        "predicted_path": [
          "ts-route-service",
          "ts-travel-service",
          "ts-preserve-service"
        ],
        "predicted_path_length": 3,
        "elapsed_seconds": 88.47,
        "gt_fault": "mem"
      }
    },
    {
      "system": "ours",
      "benchmark": "rcaeval-re2-tt",
      "case": "ts-train-service_mem_1",
      "gt_service": "ts-train-service",
      "gt_fault": "mem",
      "elapsed_seconds": 108.43,
      "evaluation": {
        "ac_at_1": true,
        "ac_at_3": true,
        "path_accuracy": null,
        "fp_handled": null,
        "top_confidence": 0.6,
        "verdict": "revised",
        "ground_truth_root_cause": "ts-train-service",
        "predicted_top_cause_service": "ts-train-service",
        "predicted_top_cause_excerpt": "ts-train-service",
        "predicted_path": [
          "ts-train-service",
          "ts-travel-service",
          "ts-preserve-service"
        ],
        "predicted_path_length": 3,
        "elapsed_seconds": 108.43,
        "gt_fault": "mem"
      }
    },
    {
      "system": "ours",
      "benchmark": "rcaeval-re2-tt",
      "case": "ts-travel-service_mem_1",
      "gt_service": "ts-travel-service",
      "gt_fault": "mem",
      "elapsed_seconds": 73.38,
      "evaluation": {
        "ac_at_1": true,
        "ac_at_3": true,
        "path_accuracy": null,
        "fp_handled": null,
        "top_confidence": 0.6,
        "verdict": "revised",
        "ground_truth_root_cause": "ts-travel-service",
        "predicted_top_cause_service": "ts-travel-service",
        "predicted_top_cause_excerpt": "ts-travel-service",
        "predicted_path": [
          "ts-travel-service",
          "ts-preserve-service"
        ],
        "predicted_path_length": 2,
        "elapsed_seconds": 73.38,
        "gt_fault": "mem"
      }
    }
  ]
}